aireport/__init__.py
aireport/aireport.egg-info/dependency_links.txt
aireport/aireport.egg-info/PKG-INFO
aireport/aireport.egg-info/SOURCES.txt
aireport/aireport.egg-info/top_level.txt
aireport/build/lib/tools/__init__.py
aireport/build/lib/tools/retools.py
aireport/build/lib/tools/tools.py
aireport/commands/__init__.py
aireport/commands/run.py
aireport/dist/aireport-0.0.0-py3.8.egg
aireport/main.py
aireport/setup.py
aireport/tools/__init__.py
aireport/tools/retools.py
aireport/tools/tools.py
aireport-0.1.12.dist-info/WHEEL
aireport-0.1.12.dist-info/METADATA
aireport-0.1.12.dist-info/RECORD
