Metadata-Version: 2.1
Name: aireport
Version: 0.1.12
Summary: 
Author: None
Requires-Python: >=3.8,<4.0
Classifier: Programming Language :: Python :: 3
Classifier: Programming Language :: Python :: 3.8
Requires-Dist: aihelper (>=0.2.5,<0.3.0)
Requires-Dist: black (>=19.10b0,<20.0)
Requires-Dist: click (>=7.1.2,<8.0.0)
Requires-Dist: numpy
Requires-Dist: pandas (>=1.0.5,<2.0.0)
